[
{"file_id": "d41586-020-03626-1", "year": 2020, "body": ""},
{"file_id": "d41586-020-02814-3", "year": 2020, "body": ""},
{"file_id": "d41586-020-02948-4", "year": 2020, "body": ""},
{"file_id": "d41586-020-02801-8", "year": 2020, "body": ""},
{"file_id": "d41586-020-02946-6", "year": 2020, "body": ""},
{"file_id": "d41586-020-02856-7", "year": 2020, "body": ""},
{"file_id": "d41586-020-02800-9", "year": 2020, "body": ""},
{"file_id": "d41586-020-02986-y", "year": 2020, "body": ""},
{"file_id": "d41586-020-02985-z", "year": 2020, "body": ""},
{"file_id": "d41586-020-03186-4", "year": 2020, "body": ""},
{"file_id": "d41586-020-03132-4", "year": 2020, "body": ""},
{"file_id": "d41586-020-03188-2", "year": 2020, "body": ""},
{"file_id": "d41586-020-03284-3", "year": 2020, "body": ""},
{"file_id": "d41586-020-03084-9", "year": 2020, "body": ""},
{"file_id": "d41586-020-03461-4", "year": 2020, "body": ""},
{"file_id": "d41586-020-03518-4", "year": 2020, "body": ""},
{"file_id": "d41586-020-03187-3", "year": 2020, "body": ""},
{"file_id": "d41586-020-03360-8", "year": 2020, "body": ""},
{"file_id": "d41586-020-02732-4", "year": 2020, "body": ""},
{"file_id": "index.html", "year": 2020, "body": ""},
{"file_id": "d41586-020-01861-0", "year": 2020, "body": ""},
{"file_id": "d41586-020-03519-3", "year": 2020, "body": ""},
{"file_id": "d41586-020-02009-w", "year": 2020, "body": ""},
{"file_id": "d41586-020-02058-1", "year": 2020, "body": ""},
{"file_id": "d41586-020-02083-0", "year": 2020, "body": ""},
{"file_id": "d41586-020-02140-8", "year": 2020, "body": ""},
{"file_id": "index.html", "year": 2020, "body": ""},
{"file_id": "d41586-020-02277-6", "year": 2020, "body": ""},
{"file_id": "d41586-020-02337-x", "year": 2020, "body": ""},
{"file_id": "d41586-020-02278-5", "year": 2020, "body": ""},
{"file_id": "d41586-020-02419-w", "year": 2020, "body": ""},
{"file_id": "index.html", "year": 2020, "body": ""},
{"file_id": "d41586-020-02400-7", "year": 2020, "body": ""},
{"file_id": "d41586-020-02418-x", "year": 2020, "body": ""},
{"file_id": "d41586-020-02497-w", "year": 2020, "body": ""},
{"file_id": "d41586-020-02544-6", "year": 2020, "body": ""},
{"file_id": "d41586-020-01811-w", "year": 2020, "body": ""},
{"file_id": "d41586-020-01221-y", "year": 2020, "body": ""},
{"file_id": "d41586-020-01363-z", "year": 2020, "body": ""},
{"file_id": "d41586-020-01315-7", "year": 2020, "body": ""},
{"file_id": "d41586-020-00922-8", "year": 2020, "body": ""},
{"file_id": "d41586-020-01445-y", "year": 2020, "body": ""},
{"file_id": "d41586-020-01444-z", "year": 2020, "body": ""},
{"file_id": "d41586-020-01518-y", "year": 2020, "body": ""},
{"file_id": "d41586-020-01452-z", "year": 2020, "body": ""},
{"file_id": "index.html", "year": 2020, "body": ""},
{"file_id": "d41586-020-01521-3", "year": 2020, "body": ""},
{"file_id": "d41586-020-01519-x", "year": 2020, "body": ""},
{"file_id": "d41586-020-01520-4", "year": 2020, "body": ""},
{"file_id": "d41586-020-01517-z", "year": 2020, "body": ""},
{"file_id": "d41586-020-01523-1", "year": 2020, "body": ""},
{"file_id": "d41586-020-00794-y", "year": 2020, "body": ""},
{"file_id": "d41586-020-01522-2", "year": 2020, "body": ""},
{"file_id": "d41586-019-03955-w", "year": 2020, "body": ""},
{"file_id": "d41586-020-00053-0", "year": 2020, "body": ""},
{"file_id": "d41586-020-00173-7", "year": 2020, "body": ""},
{"file_id": "d41586-020-00272-5", "year": 2020, "body": ""},
{"file_id": "d41586-020-00110-8", "year": 2020, "body": ""},
{"file_id": "d41586-020-00507-5", "year": 2020, "body": ""},
{"file_id": "d41586-020-00508-4", "year": 2020, "body": ""},
{"file_id": "d41586-020-00271-6", "year": 2020, "body": ""},
{"file_id": "d41586-020-00454-1", "year": 2020, "body": ""},
{"file_id": "d41586-020-00590-8", "year": 2020, "body": ""},
{"file_id": "d41586-020-00753-7", "year": 2020, "body": ""},
{"file_id": "d41586-020-00355-3", "year": 2020, "body": ""},
{"file_id": "d41586-020-00671-8", "year": 2020, "body": ""},
{"file_id": "d41586-020-01011-6", "year": 2020, "body": ""},
{"file_id": "d41586-020-01125-x", "year": 2020, "body": ""},
{"file_id": "d41586-020-00912-w", "year": 2020, "body": ""},
{"file_id": "d41586-020-01003-6", "year": 2020, "body": ""},
{"file_id": "d41586-020-01063-8", "year": 2020, "body": ""},
{"file_id": "d41586-020-00921-9", "year": 2020, "body": ""},
{"file_id": "d41586-020-01525-z", "year": 2020, "body": ""},
{"file_id": "d41586-020-01524-0", "year": 2020, "body": ""},
{"file_id": "d41586-020-02661-2", "year": 2020, "body": ""},
{"file_id": "d41586-020-01846-z", "year": 2020, "body": ""},
{"file_id": "d41586-020-02545-5", "year": 2020, "body": ""},
{"file_id": "d41586-020-02599-5", "year": 2020, "body": ""},
{"file_id": "d41586-020-01747-1", "year": 2020, "body": ""},
{"file_id": "d41586-020-02598-6", "year": 2020, "body": ""}
]